tech_analysis/__init__.py
tech_analysis/breadth.py
tech_analysis/core.py
tech_analysis/forecast.py
tech_analysis/overlays.py
tech_analysis/patterns.py
tech_analysis/performance.py
tech_analysis/price_indicators.py
tech_analysis/risk.py
tech_analysis/utils.py
tech_analysis/volume_indicators.py
tech_analysis-0.1.0.dist-info/METADATA
tech_analysis-0.1.0.dist-info/WHEEL
tech_analysis-0.1.0.dist-info/top_level.txt
tech_analysis-0.1.0.dist-info/RECORD
