Metadata-Version: 2.4
Name: tech_analysis
Version: 0.1.0
Summary: Pure Python technical analysis package
Home-page: https://github.com/bimalkshah/technicalanalysis
Author: Bimal Kumar Shah
Author-email: shah.bimal005@gmail.com
Classifier: Programming Language :: Python :: 3
Classifier: License :: OSI Approved :: MIT License
Classifier: Operating System :: OS Independent
Requires-Python: >=3.7
Requires-Dist: requests>=2.0.0
Dynamic: author
Dynamic: author-email
Dynamic: classifier
Dynamic: description
Dynamic: description-content-type
Dynamic: home-page
Dynamic: requires-dist
Dynamic: requires-python
Dynamic: summary
